{
  "id": "0c05ce17-d4e0-4436-abc9-84ee07d42403",
  "subject": "8/26",
  "body": "i'm thankful that in the five minutes before dinner was ready to come out of the oven, i emptied the dishwasher instead of looking at my phone.",
  "normalized_markdown": "i'm thankful that in the five minutes before dinner was ready to come out of the oven, i emptied the dishwasher instead of looking at my phone.",
  "publish_date": "2018-08-26T00:00:00Z",
  "description": "",
  "slug": "826-7755",
  "secondary_id": 331,
  "tags": [
    {
      "id": 1381,
      "name": "digital detox",
      "normalized_name": "digital-detox"
    },
    {
      "id": 7,
      "name": "gratitude",
      "normalized_name": "gratitude"
    },
    {
      "id": 266,
      "name": "mindfulness",
      "normalized_name": "mindfulness"
    },
    {
      "id": 15,
      "name": "personal reflection",
      "normalized_name": "personal-reflection"
    },
    {
      "id": 805,
      "name": "time management",
      "normalized_name": "time-management"
    }
  ]
}