{
  "id": "34b62851-87b9-4b13-89b2-6c28a9a770fa",
  "subject": "2/20",
  "body": "pen15, which we watched more great episodes of tonight\n\nhi-chew sent by friends\n\njeni's brambleberry crisp ice cream\n\ngetting to think about a new project at work\n\nmiso not being meanso for a little while and letting me scratch behind her neck\n\nvideo games with floaty jumps\n\nlarge mandarin oranges",
  "normalized_markdown": "pen15, which we watched more great episodes of tonight\n\nhi-chew sent by friends\n\njeni's brambleberry crisp ice cream\n\ngetting to think about a new project at work\n\nmiso not being meanso for a little while and letting me scratch behind her neck\n\nvideo games with floaty jumps\n\nlarge mandarin oranges",
  "publish_date": "2019-02-21T00:00:00Z",
  "description": "",
  "slug": "220",
  "secondary_id": 237,
  "tags": [
    {
      "id": 1244,
      "name": "food",
      "normalized_name": "food"
    },
    {
      "id": 694,
      "name": "fruit",
      "normalized_name": "fruit"
    },
    {
      "id": 1671,
      "name": "ice cream",
      "normalized_name": "ice-cream"
    },
    {
      "id": 939,
      "name": "pets",
      "normalized_name": "pets"
    },
    {
      "id": 221,
      "name": "television",
      "normalized_name": "television"
    },
    {
      "id": 232,
      "name": "video games",
      "normalized_name": "video-games"
    },
    {
      "id": 3414,
      "name": "work project",
      "normalized_name": "work-project"
    }
  ]
}