{
  "id": "3ec66c6d-38d7-4f75-8196-26aadbf3c73b",
  "subject": "",
  "body": "!\\[Image\\](/api/images/596)\\_\\_\\_PARAGRAPH\\_BREAK\\_\\_\\_!\\[Image\\](/api/images/595)\\_\\_\\_PARAGRAPH\\_BREAK\\_\\_\\_vbmmbvvbghj\\_\\_\\_PARAGRAPH\\_BREAK\\_\\_\\_!\\[Image\\](/api/images/597)",
  "normalized_markdown": "!\\[Image\\](/api/images/596)\\_\\_\\_PARAGRAPH\\_BREAK\\_\\_\\_!\\[Image\\](/api/images/595)\\_\\_\\_PARAGRAPH\\_BREAK\\_\\_\\_vbmmbvvbghj\\_\\_\\_PARAGRAPH\\_BREAK\\_\\_\\_!\\[Image\\](/api/images/597)",
  "publish_date": null,
  "description": "",
  "slug": null,
  "secondary_id": null,
  "tags": []
}