{
  "id": "a373b5d1-bfc7-48fb-bc05-b14f15290318",
  "subject": "(ac)",
  "body": "i'm thankful that tonight i had a really quite wonderful chat w my brother e that was meaningful (to both of us i think). i'm thankful that we are on a similar page intellectually/religiously/socially which means that we were able to each understand what the other was saying. i'm thankful that the shitty situation of our parents has only driven us closer. i'm thankful that we're not afflicted by social taboos which means that for us no topic is off limits. i'm thankful that we discussed marriage and n. i'm thankful that i know my brother is a good person and that he's not going to judge me for what i say. i'm thankful that my brother knows how to critique my ideas without being patronising or making me feel like his younger brother. i'm thankful that i'm even able to remain this close to brother even when we are so far apart from each other geographically. i'm thankful that i know that my brother and i will remain this close in the future. i'm thankful for my family\n\n\\- ac (7/5/17). [https://youtu.be/7Ej6g3KhinM](https://youtu.be/7Ej6g3KhinM)\n\n[what are you thankful for?](https://docs.google.com/forms/d/1X6z1T5sSBXxFpfGI7gPZzQIp_qgkDCsVVCLV4yrw1a4/edit?usp=forms_home&ths=true)",
  "normalized_markdown": "i'm thankful that tonight i had a really quite wonderful chat w my brother e that was meaningful (to both of us i think). i'm thankful that we are on a similar page intellectually/religiously/socially which means that we were able to each understand what the other was saying. i'm thankful that the shitty situation of our parents has only driven us closer. i'm thankful that we're not afflicted by social taboos which means that for us no topic is off limits. i'm thankful that we discussed marriage and n. i'm thankful that i know my brother is a good person and that he's not going to judge me for what i say. i'm thankful that my brother knows how to critique my ideas without being patronising or making me feel like his younger brother. i'm thankful that i'm even able to remain this close to brother even when we are so far apart from each other geographically. i'm thankful that i know that my brother and i will remain this close in the future. i'm thankful for my family\n\n\\- ac (7/5/17). [https://youtu.be/7Ej6g3KhinM](https://youtu.be/7Ej6g3KhinM)\n\n[what are you thankful for?](https://docs.google.com/forms/d/1X6z1T5sSBXxFpfGI7gPZzQIp_qgkDCsVVCLV4yrw1a4/edit?usp=forms_home&ths=true)",
  "publish_date": "2017-07-16T00:00:00Z",
  "description": "",
  "slug": "ac",
  "secondary_id": 735,
  "tags": [
    {
      "id": 288,
      "name": "communication",
      "normalized_name": "communication"
    },
    {
      "id": 339,
      "name": "family relationships",
      "normalized_name": "family-relationships"
    },
    {
      "id": 7,
      "name": "gratitude",
      "normalized_name": "gratitude"
    },
    {
      "id": 2357,
      "name": "intellectual connection",
      "normalized_name": "intellectual-connection"
    },
    {
      "id": 3598,
      "name": "marriage discussion",
      "normalized_name": "marriage-discussion"
    },
    {
      "id": 2358,
      "name": "social taboos",
      "normalized_name": "social-taboos"
    }
  ]
}