{
  "id": "d6681250-bbc7-490a-81de-31998c2ea5e7",
  "subject": "2/9",
  "body": "i'm thankful for [the new rhye album](https://open.spotify.com/album/6yoGOJsTjU7w2amKcUUX7S?si=K-xwdjidRuCXk55c53JMNg), which is exquisitely soft.\n\ni'm thankful for [this shiba inu spooning with a cat in the sun](https://www.instagram.com/p/BcY5YNVndHa/).\n\ni'm thankful that [the bauhaus designed a socialist utopia for penguins](https://twitter.com/sylvia__north/status/961281998806372352).\n\ni'm thankful for [this post on theology and _the good place_](https://theoutline.com/post/3327/the-good-place-religion-theology?zd=3&zi=asvwh7no).\n\ni'm thankful for this clowning on [benioff and weiss's _star wars_](https://twitter.com/petridishes/status/961024905599967234).\n\ni'm thankful that it's not too late to sign up for [kkwweekly](https://tinyletter.com/kkwweekkly), where [evie](https://twitter.com/ohevie) will summarize the content in kim's app every week.\n\ni'm thankful for kim and kanye in tokyo together, [buying manga](https://kotaku.com/kim-kardashian-is-just-like-you-she-shops-for-manga-1822826540).\n\ni'm thankful to hope that at some point we all have the joy of [kid cudi's dancing in this video](https://twitter.com/AyeshaASiddiqi/status/961846036380631040).",
  "normalized_markdown": "i'm thankful for [the new rhye album](https://open.spotify.com/album/6yoGOJsTjU7w2amKcUUX7S?si=K-xwdjidRuCXk55c53JMNg), which is exquisitely soft.\n\ni'm thankful for [this shiba inu spooning with a cat in the sun](https://www.instagram.com/p/BcY5YNVndHa/).\n\ni'm thankful that [the bauhaus designed a socialist utopia for penguins](https://twitter.com/sylvia__north/status/961281998806372352).\n\ni'm thankful for [this post on theology and _the good place_](https://theoutline.com/post/3327/the-good-place-religion-theology?zd=3&zi=asvwh7no).\n\ni'm thankful for this clowning on [benioff and weiss's _star wars_](https://twitter.com/petridishes/status/961024905599967234).\n\ni'm thankful that it's not too late to sign up for [kkwweekly](https://tinyletter.com/kkwweekkly), where [evie](https://twitter.com/ohevie) will summarize the content in kim's app every week.\n\ni'm thankful for kim and kanye in tokyo together, [buying manga](https://kotaku.com/kim-kardashian-is-just-like-you-she-shops-for-manga-1822826540).\n\ni'm thankful to hope that at some point we all have the joy of [kid cudi's dancing in this video](https://twitter.com/AyeshaASiddiqi/status/961846036380631040).",
  "publish_date": "2018-02-09T00:00:00Z",
  "description": "",
  "slug": "29",
  "secondary_id": 526,
  "tags": [
    {
      "id": 2097,
      "name": "celebrity news",
      "normalized_name": "celebrity-news"
    },
    {
      "id": 2098,
      "name": "design",
      "normalized_name": "design"
    },
    {
      "id": 326,
      "name": "humor",
      "normalized_name": "humor"
    },
    {
      "id": 92,
      "name": "music appreciation",
      "normalized_name": "music-appreciation"
    },
    {
      "id": 5,
      "name": "pop culture",
      "normalized_name": "pop-culture"
    },
    {
      "id": 83,
      "name": "social media",
      "normalized_name": "social-media"
    },
    {
      "id": 2096,
      "name": "theology",
      "normalized_name": "theology"
    }
  ]
}