{
  "id": "d76551e3-6dad-47b6-ab59-cdb70f044b10",
  "subject": "(c)(13)",
  "body": "i’m thankful to be lost. i’m thankful to know—and to admit—i’m lost. i’m thankful that being lost is a necessary step in understanding what i want out of the world around me; that being lost provides a very simple set of responsibilities and expectations: figure out what you desire and take care of those you love—including yourself. \n\ni’m thankful to have now spent around a year admitting i’m lost, but i’m even more thankful now to feel as though being lost isn’t something to be feared, but embraced. \n\ni’m thankful to recognize i’ve done a poor job of embracing “the lost” over my last year; that i have verbalized and tortured myself with the state of being, but have rushed quickly to form order—or at times lack thereof as a protest to the seemingly orderlessness of it. i’m thankful now to recognize i must embrace the lost and open my eyes again. \n\ni’m thankful for the new mindset i have adopted toward being lost; a mindset which looks back to the opportunities i have accepted in my rush to order as spaces to explore who i am and who i wish to be. \n\ni’m thankful i called my grandfather to wish him a happy birthday yesterday. i’m thankful the when i called, my family was sat around him at the table, enjoying birthday cake and ice cream. i’m thankful he went around the table telling me where each person was sat, and to have been able to see their dinning room and faces around me, despite my lack of being there. i’m thankful for the sense of homesickness this brought me, of suddenly wanting to be back with the people i love and who love me—no matter how lost i may feel. \n\ni’m thankful for the frustratingly complex feelings of love and longing, because i know they are what compose the human experience. i’m thankful that these complex feelings move; that the anxiety and uncomfortableness can wear thin and leave in their wake a longing. i’m thankful that often times the feelings left once the waters settle are even more complex and confusing than the feelings which preceded them, because this is what it means to live. \n\ni’m thankful to be writing again, and i’m hopeful it will help me understand just how i want to live. \n\nthank you\n\n\\- c (11/15/17). \n\n[previously](https://tinyletter.com/thankyounotes/letters/c-12)\n\n[what are you thankful for?](https://docs.google.com/forms/d/1X6z1T5sSBXxFpfGI7gPZzQIp_qgkDCsVVCLV4yrw1a4/edit)",
  "normalized_markdown": "i’m thankful to be lost. i’m thankful to know—and to admit—i’m lost. i’m thankful that being lost is a necessary step in understanding what i want out of the world around me; that being lost provides a very simple set of responsibilities and expectations: figure out what you desire and take care of those you love—including yourself. \n\ni’m thankful to have now spent around a year admitting i’m lost, but i’m even more thankful now to feel as though being lost isn’t something to be feared, but embraced. \n\ni’m thankful to recognize i’ve done a poor job of embracing “the lost” over my last year; that i have verbalized and tortured myself with the state of being, but have rushed quickly to form order—or at times lack thereof as a protest to the seemingly orderlessness of it. i’m thankful now to recognize i must embrace the lost and open my eyes again. \n\ni’m thankful for the new mindset i have adopted toward being lost; a mindset which looks back to the opportunities i have accepted in my rush to order as spaces to explore who i am and who i wish to be. \n\ni’m thankful i called my grandfather to wish him a happy birthday yesterday. i’m thankful the when i called, my family was sat around him at the table, enjoying birthday cake and ice cream. i’m thankful he went around the table telling me where each person was sat, and to have been able to see their dinning room and faces around me, despite my lack of being there. i’m thankful for the sense of homesickness this brought me, of suddenly wanting to be back with the people i love and who love me—no matter how lost i may feel. \n\ni’m thankful for the frustratingly complex feelings of love and longing, because i know they are what compose the human experience. i’m thankful that these complex feelings move; that the anxiety and uncomfortableness can wear thin and leave in their wake a longing. i’m thankful that often times the feelings left once the waters settle are even more complex and confusing than the feelings which preceded them, because this is what it means to live. \n\ni’m thankful to be writing again, and i’m hopeful it will help me understand just how i want to live. \n\nthank you\n\n\\- c (11/15/17). \n\n[previously](https://tinyletter.com/thankyounotes/letters/c-12)\n\n[what are you thankful for?](https://docs.google.com/forms/d/1X6z1T5sSBXxFpfGI7gPZzQIp_qgkDCsVVCLV4yrw1a4/edit)",
  "publish_date": "2017-11-17T00:00:00Z",
  "description": "",
  "slug": "c13",
  "secondary_id": 612,
  "tags": [
    {
      "id": 3562,
      "name": "embracing uncertainty",
      "normalized_name": "embracing-uncertainty"
    },
    {
      "id": 2215,
      "name": "emotional complexity",
      "normalized_name": "emotional-complexity"
    },
    {
      "id": 1133,
      "name": "family connections",
      "normalized_name": "family-connections"
    },
    {
      "id": 266,
      "name": "mindfulness",
      "normalized_name": "mindfulness"
    },
    {
      "id": 51,
      "name": "personal growth",
      "normalized_name": "personal-growth"
    },
    {
      "id": 856,
      "name": "self-discovery",
      "normalized_name": "self-discovery"
    }
  ]
}