{
  "id": "ef1ef60a-3a03-4f85-bcb2-cf62a19ac1f2",
  "subject": "4/5",
  "body": "i'm thankful for [this thread of pictures of afghan hounds](https://twitter.com/mollybackes/status/981380494758735874).",
  "normalized_markdown": "i'm thankful for [this thread of pictures of afghan hounds](https://twitter.com/mollybackes/status/981380494758735874).",
  "publish_date": "2018-04-05T00:00:00Z",
  "description": "",
  "slug": "45",
  "secondary_id": 471,
  "tags": [
    {
      "id": 2008,
      "name": "afghan hounds",
      "normalized_name": "afghan-hounds"
    },
    {
      "id": 2010,
      "name": "animal appreciation",
      "normalized_name": "animal-appreciation"
    },
    {
      "id": 2009,
      "name": "dog breeds",
      "normalized_name": "dog-breeds"
    },
    {
      "id": 220,
      "name": "photography",
      "normalized_name": "photography"
    },
    {
      "id": 83,
      "name": "social media",
      "normalized_name": "social-media"
    }
  ]
}